torch_tomo/CSET_pytorch.py
torch_tomo/__init__.py
torch_tomo/tilt_series_alignment.py
torch_tomo-0.1.2.dist-info/LICENSE
torch_tomo-0.1.2.dist-info/METADATA
torch_tomo-0.1.2.dist-info/WHEEL
torch_tomo-0.1.2.dist-info/top_level.txt
torch_tomo-0.1.2.dist-info/RECORD
