Metadata-Version: 2.1
Name: torch-tomo
Version: 0.1.2
Summary: Tools for Electron tomography
Home-page: https://github.com/jinseuk56
Author: Jinseok Ryu
Author-email: jinseuk56@gmail.com
License-File: LICENSE
